bastion/__init__.py
bastion/bastion_metadata.py
bastion/breach_detection.py
bastion/config.py
bastion/csv_export.py
bastion/db.py
bastion/entropy.py
bastion/entropy_dice.py
bastion/entropy_infnoise.py
bastion/entropy_system_rng.py
bastion/entropy_visual.py
bastion/entropy_yubikey.py
bastion/entropy_yubikey_openpgp.py
bastion/icon_manager.py
bastion/label_spec.py
bastion/linking.py
bastion/macos_automation.py
bastion/mermaid.py
bastion/migration.py
bastion/migration_yubikey_fields.py
bastion/models.py
bastion/op_client.py
bastion/passkey_health.py
bastion/people.py
bastion/planning.py
bastion/reports.py
bastion/risk_analysis.py
bastion/service_rules.json
bastion/tag_operations.py
bastion/token_analyzer.py
bastion/token_tag_manager.py
bastion/token_validator.py
bastion/username_generator.py
bastion/validation.py
bastion/validation_rules.py
bastion/yubikey_cache.py
bastion/yubikey_service.py
bastion/cli/__init__.py
bastion/cli/app.py
bastion/cli/console.py
bastion/cli/helpers.py
bastion/cli/main.py
bastion/cli/yubikey_helpers.py
bastion/cli/commands/__init__.py
bastion/cli/commands/analysis_commands.py
bastion/cli/commands/analyze.py
bastion/cli/commands/audit.py
bastion/cli/commands/check.py
bastion/cli/commands/cleanup.py
bastion/cli/commands/config.py
bastion/cli/commands/config_commands.py
bastion/cli/commands/entropy.py
bastion/cli/commands/export.py
bastion/cli/commands/find.py
bastion/cli/commands/generate.py
bastion/cli/commands/generate_commands.py
bastion/cli/commands/icon_commands.py
bastion/cli/commands/icons.py
bastion/cli/commands/maintenance_commands.py
bastion/cli/commands/migration_commands.py
bastion/cli/commands/migrations.py
bastion/cli/commands/op_commands.py
bastion/cli/commands/passkey.py
bastion/cli/commands/relationship_commands.py
bastion/cli/commands/relationships.py
bastion/cli/commands/report.py
bastion/cli/commands/rollback.py
bastion/cli/commands/show.py
bastion/cli/commands/sigchain_commands.py
bastion/cli/commands/sync.py
bastion_security-0.3.0.dist-info/METADATA
bastion_security-0.3.0.dist-info/WHEEL
bastion_security-0.3.0.dist-info/entry_points.txt
bastion_security-0.3.0.dist-info/RECORD
