Metadata-Version: 2.4
Name: bastion-security
Version: 0.3.0
Summary: Password rotation tracking, deterministic username generation, and entropy management with 1Password integration
Project-URL: Homepage, https://github.com/jakehertenstein/bastion
Project-URL: Repository, https://github.com/jakehertenstein/bastion
Project-URL: Documentation, https://github.com/jakehertenstein/bastion/tree/main/docs
Project-URL: Issues, https://github.com/jakehertenstein/bastion/issues
Author-email: Jake Hertenstein <bastion@jakehertenstein.anonaddy.com>
License: PolyForm Noncommercial 1.0.0
Keywords: 1password,entropy,password-manager,password-rotation,security,username-generator,yubikey
Classifier: Development Status :: 4 - Beta
Classifier: Environment :: Console
Classifier: Intended Audience :: Developers
Classifier: Intended Audience :: System Administrators
Classifier: Operating System :: OS Independent
Classifier: Programming Language :: Python :: 3.11
Classifier: Programming Language :: Python :: 3.12
Classifier: Topic :: Security
Classifier: Topic :: Security :: Cryptography
Classifier: Typing :: Typed
Requires-Python: >=3.11
Requires-Dist: bastion-core
Requires-Dist: cryptography>=42.0.0
Requires-Dist: httpx>=0.27.0
Requires-Dist: matplotlib>=3.8.0
Requires-Dist: numpy>=1.26.0
Requires-Dist: pendulum>=3.0.0
Requires-Dist: pydantic>=2.7.0
Requires-Dist: rich>=13.9.0
Requires-Dist: typer>=0.12.0
